{
    "overrides": [
        {
            "files": [
                "src/**/*.js"
            ],
            "extends": [
                "standard"
            ],
            "rules": {
                "indent": [
                    "error",
                    4
                ],
                "semi": [
                    "error",
                    "never"
                ],
                "quotes": [
                    "error",
                    "backtick"
                ]
            }
        }
    ]
}